mafia_schedule/__init__.py
mafia_schedule/configuration.py
mafia_schedule/game.py
mafia_schedule/helpers.py
mafia_schedule/metrics.py
mafia_schedule/optimize_opponents.py
mafia_schedule/optimize_seats.py
mafia_schedule/output.py
mafia_schedule/player.py
mafia_schedule/round.py
mafia_schedule/schedule.py
mafia_schedule/schedule_factory.py
mafia_schedule-0.0.6.dist-info/LICENSE
mafia_schedule-0.0.6.dist-info/METADATA
mafia_schedule-0.0.6.dist-info/WHEEL
mafia_schedule-0.0.6.dist-info/top_level.txt
mafia_schedule-0.0.6.dist-info/RECORD
