Metadata-Version: 2.1
Name: mafia-schedule
Version: 0.0.6
Summary: This is package to generate and work with schedules of mafia tournaments
Home-page: https://github.com/dimtom/MafSchedule
Author: Dmitry Bimatov
Author-email: dbimatov@gmail.com
License: UNKNOWN
Platform: UNKNOWN
Classifier: Programming Language :: Python
Classifier: Programming Language :: Python :: 3
Classifier: Programming Language :: Python :: 3.9
Classifier: Environment :: Console
Classifier: Operating System :: OS Independent
Classifier: License :: OSI Approved :: GNU General Public License v3 (GPLv3)
Requires-Python: >=3.9
License-File: LICENSE
